standlib/__init__.py
standlib/double.py
standlib-0.0.8.dist-info/LICENSE
standlib-0.0.8.dist-info/METADATA
standlib-0.0.8.dist-info/WHEEL
standlib-0.0.8.dist-info/top_level.txt
standlib-0.0.8.dist-info/RECORD
