Metadata-Version: 2.1
Name: standlib
Version: 0.0.8
Summary: A custom standard library module for Python
Home-page: https://github.com/BrunoCiccarino/standlib
Author: BrunoCiccarino
Author-email: ciccabr9@gmail.com
Classifier: Programming Language :: Python :: 3
Classifier: Operating System :: OS Independent
Requires-Python: >=3.6
License-File: LICENSE
